flask_logging_extras/__init__.py
Flask_Logging_Extras-2.0.0.dist-info/LICENSE
Flask_Logging_Extras-2.0.0.dist-info/METADATA
Flask_Logging_Extras-2.0.0.dist-info/WHEEL
Flask_Logging_Extras-2.0.0.dist-info/top_level.txt
Flask_Logging_Extras-2.0.0.dist-info/RECORD
