Metadata-Version: 2.1
Name: Flask-Logging-Extras
Version: 2.0.0
Summary: Extra logging functionality for Flask apps
Home-page: https://github.com/gergelypolonkai/flask-logging-extras
Author: Gergely Polonkai
Author-email: gergely@polonkai.eu
License: MIT
Keywords: flask,logging
Platform: any
Classifier: Development Status :: 4 - Beta
Classifier: Environment :: Web Environment
Classifier: Intended Audience :: Developers
Classifier: License :: OSI Approved :: MIT License
Classifier: Operating System :: OS Independent
Classifier: Programming Language :: Python
Classifier: Programming Language :: Python :: 2.7
Classifier: Programming Language :: Python :: 3
Classifier: Programming Language :: Python :: 3.3
Classifier: Programming Language :: Python :: 3.4
Classifier: Programming Language :: Python :: 3.5
Classifier: Programming Language :: Python :: 3.6
Classifier: Topic :: Internet :: WWW/HTTP :: Dynamic Content
Classifier: Topic :: Software Development :: Libraries :: Python Modules
Requires-Dist: Flask
